evil_py/__init__.py
evil_py/evil.py
evilpy/__init__.py
evilpy/evil.py
except_py/__init__.py
except_py/exception.py
exception.py-0.4.dist-info/METADATA
exception.py-0.4.dist-info/WHEEL
exception.py-0.4.dist-info/top_level.txt
exception.py-0.4.dist-info/RECORD
