Metadata-Version: 2.1
Name: exception.py
Version: 0.4
Summary: Except.Py that Make *unexceptional* problem
Home-page: 
Author: cyan
Author-email: 
